odoo/addons/geoengine_swisstopo/__init__.py
odoo/addons/geoengine_swisstopo/__manifest__.py
odoo/addons/geoengine_swisstopo/geo_view/__init__.py
odoo/addons/geoengine_swisstopo/geo_view/geo_raster_layer.py
odoo/addons/geoengine_swisstopo/geo_view/geo_raster_layer_view.xml
odoo/addons/geoengine_swisstopo/i18n/geoengine_swisstopo.pot
odoo/addons/geoengine_swisstopo/static/description/icon.png
odoo/addons/geoengine_swisstopo/static/src/js/.eslintrc
odoo/addons/geoengine_swisstopo/static/src/js/geoengine_swisstopo.js
odoo/addons/geoengine_swisstopo/views/geoengine_swisstopo_view.xml
odoo11_addon_geoengine_swisstopo-11.0.1.0.0.99.dev2.dist-info/METADATA
odoo11_addon_geoengine_swisstopo-11.0.1.0.0.99.dev2.dist-info/WHEEL
odoo11_addon_geoengine_swisstopo-11.0.1.0.0.99.dev2.dist-info/top_level.txt
odoo11_addon_geoengine_swisstopo-11.0.1.0.0.99.dev2.dist-info/RECORD
